copyist/__init__.py
copyist/cli.py
copyist/exceptions.py
copyist/helpers.py
copyist/sync.py
copyist-0.3.dist-info/LICENSE
copyist-0.3.dist-info/METADATA
copyist-0.3.dist-info/WHEEL
copyist-0.3.dist-info/entry_points.txt
copyist-0.3.dist-info/top_level.txt
copyist-0.3.dist-info/RECORD
