Metadata-Version: 2.1
Name: copyist
Version: 0.3
Summary: A tool to keep your configuration synced between repositories
Home-page: https://github.com/Polyconseil/copyist
Author: Polyconseil
Author-email: opensource+copyist@polyconseil.fr
License: UNKNOWN
Keywords: tools configuration generation sync
Platform: UNKNOWN
Classifier: Development Status :: 3 - Alpha
Classifier: Environment :: Console
Classifier: Intended Audience :: Developers
Classifier: License :: OSI Approved :: MIT License
Classifier: Natural Language :: English
Classifier: Programming Language :: Python
Classifier: Programming Language :: Python :: 3
Classifier: Programming Language :: Python :: 3.7
Classifier: Programming Language :: Python :: 3.8
Classifier: Topic :: Software Development
Classifier: Topic :: Software Development :: Code Generators
Requires-Dist: tomlkit
Requires-Dist: importlib-metadata ; python_version < "3.8"
Provides-Extra: dev
Requires-Dist: isort ; extra == 'dev'
Requires-Dist: black ; extra == 'dev'
Requires-Dist: check-manifest ; extra == 'dev'
Requires-Dist: zest.releaser ; extra == 'dev'
